markdown2json/__init__.py
markdown2json/parser.py
markdown2json/helpers/__init__.py
markdown2json/helpers/document_analyzer.py
markdown2json/models/__init__.py
markdown2json/models/enums.py
markdown2json/utils/__init__.py
markdown2json/utils/extractors.py
markdown2json/utils/llm_processors.py
markdown2json/utils/text_processors.py
markdown2json-0.1.0.dist-info/METADATA
markdown2json-0.1.0.dist-info/WHEEL
markdown2json-0.1.0.dist-info/top_level.txt
markdown2json-0.1.0.dist-info/RECORD
