Metadata-Version: 2.4
Name: markdown2json
Version: 0.1.0
Summary: A Python package to convert markdown content to structured JSON
Home-page: https://github.com/ekbanasolutions/markdown2json
Author: Vaghawan Ojha, Sadikshya Gyawali, Manish Dahal, Manish Awale, Ashwini Mandal
Author-email: vaghawan.ojha@ekbana.net, sadikshya.gyawali@ekbana.info, manish.dahal@ekbana.info, manish.awale@ekbana.info, ashwini.mandal@ekbana.info
Classifier: Programming Language :: Python :: 3
Classifier: License :: OSI Approved :: MIT License
Classifier: Operating System :: OS Independent
Requires-Python: >=3.8
Requires-Dist: Markdown==3.7
Requires-Dist: beautifulsoup4==4.12.3
Requires-Dist: anthropic==0.43.0
Requires-Dist: openai==1.59.7
Requires-Dist: ollama==0.4.7
Requires-Dist: python-dotenv==1.0.1
Requires-Dist: markdown-katex==202406.1035
Requires-Dist: markdown-it-py==3.0.0
Dynamic: author
Dynamic: author-email
Dynamic: classifier
Dynamic: description
Dynamic: description-content-type
Dynamic: home-page
Dynamic: requires-dist
Dynamic: requires-python
Dynamic: summary
